[{"id": 0, "ori_id": 0, "text": "keyboard", "name": "keyboard", "children": [{"ori_id": 2, "name": "frame", "id": 1, "text": "frame", "objs": ["original-116"]}, {"ori_id": 3, "name": "key", "id": 2, "text": "key", "objs": ["original-49"]}, {"ori_id": 4, "name": "key", "id": 3, "text": "key", "objs": ["original-63"]}, {"ori_id": 5, "name": "key", "id": 4, "text": "key", "objs": ["original-64"]}, {"ori_id": 6, "name": "key", "id": 5, "text": "key", "objs": ["original-50"]}, {"ori_id": 7, "name": "key", "id": 6, "text": "key", "objs": ["original-38"]}, {"ori_id": 8, "name": "key", "id": 7, "text": "key", "objs": ["original-39"]}, {"ori_id": 9, "name": "key", "id": 8, "text": "key", "objs": ["original-51"]}, {"ori_id": 10, "name": "key", "id": 9, "text": "key", "objs": ["original-65"]}, {"ori_id": 11, "name": "key", "id": 10, "text": "key", "objs": ["original-40"]}, {"ori_id": 12, "name": "key", "id": 11, "text": "key", "objs": ["original-52"]}, {"ori_id": 13, "name": "key", "id": 12, "text": "key", "objs": ["original-66"]}, {"ori_id": 14, "name": "key", "id": 13, "text": "key", "objs": ["original-53"]}, {"ori_id": 15, "name": "key", "id": 14, "text": "key", "objs": ["original-58"]}, {"ori_id": 16, "name": "key", "id": 15, "text": "key", "objs": ["original-45"]}, {"ori_id": 17, "name": "key", "id": 16, "text": "key", "objs": ["original-33"]}, {"ori_id": 18, "name": "key", "id": 17, "text": "key", "objs": ["original-31"]}, {"ori_id": 19, "name": "key", "id": 18, "text": "key", "objs": ["original-32"]}, {"ori_id": 20, "name": "key", "id": 19, "text": "key", "objs": ["original-44"]}, {"ori_id": 21, "name": "key", "id": 20, "text": "key", "objs": ["original-57"]}, {"ori_id": 22, "name": "key", "id": 21, "text": "key", "objs": ["original-56"]}, {"ori_id": 23, "name": "key", "id": 22, "text": "key", "objs": ["original-43"]}, {"ori_id": 24, "name": "key", "id": 23, "text": "key", "objs": ["original-3"]}, {"ori_id": 25, "name": "key", "id": 24, "text": "key", "objs": ["original-4"]}, {"ori_id": 26, "name": "key", "id": 25, "text": "key", "objs": ["original-55"]}, {"ori_id": 27, "name": "key", "id": 26, "text": "key", "objs": ["original-70"]}, {"ori_id": 28, "name": "key", "id": 27, "text": "key", "objs": ["original-71"]}, {"ori_id": 29, "name": "key", "id": 28, "text": "key", "objs": ["original-72"]}, {"ori_id": 30, "name": "key", "id": 29, "text": "key", "objs": ["original-73"]}, {"ori_id": 31, "name": "key", "id": 30, "text": "key", "objs": ["original-74"]}, {"ori_id": 32, "name": "key", "id": 31, "text": "key", "objs": ["original-76"]}, {"ori_id": 33, "name": "key", "id": 32, "text": "key", "objs": ["original-75"]}, {"ori_id": 34, "name": "key", "id": 33, "text": "key", "objs": ["original-77"]}, {"ori_id": 35, "name": "key", "id": 34, "text": "key", "objs": ["original-78"]}, {"ori_id": 36, "name": "key", "id": 35, "text": "key", "objs": ["original-79"]}, {"ori_id": 37, "name": "key", "id": 36, "text": "key", "objs": ["original-80"]}, {"ori_id": 38, "name": "key", "id": 37, "text": "key", "objs": ["original-81"]}, {"ori_id": 39, "name": "key", "id": 38, "text": "key", "objs": ["original-82"]}, {"ori_id": 40, "name": "key", "id": 39, "text": "key", "objs": ["original-12"]}, {"ori_id": 41, "name": "key", "id": 40, "text": "key", "objs": ["original-11"]}, {"ori_id": 42, "name": "key", "id": 41, "text": "key", "objs": ["original-10"]}, {"ori_id": 43, "name": "key", "id": 42, "text": "key", "objs": ["original-1"]}, {"ori_id": 44, "name": "key", "id": 43, "text": "key", "objs": ["original-7"]}, {"ori_id": 45, "name": "key", "id": 44, "text": "key", "objs": ["original-6"]}, {"ori_id": 46, "name": "key", "id": 45, "text": "key", "objs": ["original-8"]}, {"ori_id": 47, "name": "key", "id": 46, "text": "key", "objs": ["original-9"]}, {"ori_id": 48, "name": "key", "id": 47, "text": "key", "objs": ["original-13"]}, {"ori_id": 49, "name": "key", "id": 48, "text": "key", "objs": ["original-14"]}, {"ori_id": 50, "name": "key", "id": 49, "text": "key", "objs": ["original-15"]}, {"ori_id": 51, "name": "key", "id": 50, "text": "key", "objs": ["original-16"]}, {"ori_id": 52, "name": "key", "id": 51, "text": "key", "objs": ["original-17"]}, {"ori_id": 53, "name": "key", "id": 52, "text": "key", "objs": ["original-18"]}, {"ori_id": 54, "name": "key", "id": 53, "text": "key", "objs": ["original-19"]}, {"ori_id": 55, "name": "key", "id": 54, "text": "key", "objs": ["original-20"]}, {"ori_id": 56, "name": "key", "id": 55, "text": "key", "objs": ["original-67"]}, {"ori_id": 57, "name": "key", "id": 56, "text": "key", "objs": ["original-54"]}, {"ori_id": 58, "name": "key", "id": 57, "text": "key", "objs": ["original-41"]}, {"ori_id": 59, "name": "key", "id": 58, "text": "key", "objs": ["original-42"]}, {"ori_id": 60, "name": "key", "id": 59, "text": "key", "objs": ["original-68"]}, {"ori_id": 61, "name": "key", "id": 60, "text": "key", "objs": ["original-69"]}, {"ori_id": 62, "name": "key", "id": 61, "text": "key", "objs": ["original-84"]}, {"ori_id": 63, "name": "key", "id": 62, "text": "key", "objs": ["original-83"]}, {"ori_id": 64, "name": "key", "id": 63, "text": "key", "objs": ["original-85"]}, {"ori_id": 65, "name": "key", "id": 64, "text": "key", "objs": ["original-108"]}, {"ori_id": 66, "name": "key", "id": 65, "text": "key", "objs": ["original-109"]}, {"ori_id": 67, "name": "key", "id": 66, "text": "key", "objs": ["original-110"]}, {"ori_id": 68, "name": "key", "id": 67, "text": "key", "objs": ["original-111"]}, {"ori_id": 69, "name": "key", "id": 68, "text": "key", "objs": ["original-112"]}, {"ori_id": 70, "name": "key", "id": 69, "text": "key", "objs": ["original-5"]}, {"ori_id": 71, "name": "key", "id": 70, "text": "key", "objs": ["original-113"]}, {"ori_id": 72, "name": "key", "id": 71, "text": "key", "objs": ["original-114"]}, {"ori_id": 73, "name": "key", "id": 72, "text": "key", "objs": ["original-115"]}, {"ori_id": 74, "name": "key", "id": 73, "text": "key", "objs": ["original-104"]}, {"ori_id": 75, "name": "key", "id": 74, "text": "key", "objs": ["original-105"]}, {"ori_id": 76, "name": "key", "id": 75, "text": "key", "objs": ["original-95"]}, {"ori_id": 77, "name": "key", "id": 76, "text": "key", "objs": ["original-97"]}, {"ori_id": 78, "name": "key", "id": 77, "text": "key", "objs": ["original-96"]}, {"ori_id": 79, "name": "key", "id": 78, "text": "key", "objs": ["original-92"]}, {"ori_id": 80, "name": "key", "id": 79, "text": "key", "objs": ["original-94"]}, {"ori_id": 81, "name": "key", "id": 80, "text": "key", "objs": ["original-90"]}, {"ori_id": 82, "name": "key", "id": 81, "text": "key", "objs": ["original-89"]}, {"ori_id": 83, "name": "key", "id": 82, "text": "key", "objs": ["original-86"]}, {"ori_id": 84, "name": "key", "id": 83, "text": "key", "objs": ["original-30"]}, {"ori_id": 85, "name": "key", "id": 84, "text": "key", "objs": ["original-29"]}, {"ori_id": 86, "name": "key", "id": 85, "text": "key", "objs": ["original-21"]}, {"ori_id": 87, "name": "key", "id": 86, "text": "key", "objs": ["original-25"]}, {"ori_id": 88, "name": "key", "id": 87, "text": "key", "objs": ["original-87"]}, {"ori_id": 89, "name": "key", "id": 88, "text": "key", "objs": ["original-103"]}, {"ori_id": 90, "name": "key", "id": 89, "text": "key", "objs": ["original-88"]}, {"ori_id": 91, "name": "key", "id": 90, "text": "key", "objs": ["original-91"]}, {"ori_id": 92, "name": "key", "id": 91, "text": "key", "objs": ["original-93"]}, {"ori_id": 93, "name": "key", "id": 92, "text": "key", "objs": ["original-106"]}, {"ori_id": 94, "name": "key", "id": 93, "text": "key", "objs": ["original-107"]}, {"ori_id": 95, "name": "key", "id": 94, "text": "key", "objs": ["original-98"]}, {"ori_id": 96, "name": "key", "id": 95, "text": "key", "objs": ["original-99"]}, {"ori_id": 97, "name": "key", "id": 96, "text": "key", "objs": ["original-100"]}, {"ori_id": 98, "name": "key", "id": 97, "text": "key", "objs": ["original-101"]}, {"ori_id": 99, "name": "key", "id": 98, "text": "key", "objs": ["original-102"]}, {"ori_id": 100, "name": "key", "id": 99, "text": "key", "objs": ["original-28"]}, {"ori_id": 101, "name": "key", "id": 100, "text": "key", "objs": ["original-27"]}, {"ori_id": 102, "name": "key", "id": 101, "text": "key", "objs": ["original-26"]}, {"ori_id": 103, "name": "key", "id": 102, "text": "key", "objs": ["original-24"]}, {"ori_id": 104, "name": "key", "id": 103, "text": "key", "objs": ["original-23"]}, {"ori_id": 105, "name": "key", "id": 104, "text": "key", "objs": ["original-22"]}, {"ori_id": 106, "name": "key", "id": 105, "text": "key", "objs": ["original-2"]}, {"ori_id": 107, "name": "key", "id": 106, "text": "key", "objs": ["original-34"]}, {"ori_id": 108, "name": "key", "id": 107, "text": "key", "objs": ["original-35"]}, {"ori_id": 109, "name": "key", "id": 108, "text": "key", "objs": ["original-36"]}, {"ori_id": 110, "name": "key", "id": 109, "text": "key", "objs": ["original-37"]}, {"ori_id": 111, "name": "key", "id": 110, "text": "key", "objs": ["original-48"]}, {"ori_id": 112, "name": "key", "id": 111, "text": "key", "objs": ["original-47"]}, {"ori_id": 113, "name": "key", "id": 112, "text": "key", "objs": ["original-46"]}, {"ori_id": 114, "name": "key", "id": 113, "text": "key", "objs": ["original-59"]}, {"ori_id": 115, "name": "key", "id": 114, "text": "key", "objs": ["original-60"]}, {"ori_id": 116, "name": "key", "id": 115, "text": "key", "objs": ["original-61"]}, {"ori_id": 117, "name": "key", "id": 116, "text": "key", "objs": ["original-62"]}], "objs": ["original-116", "original-49", "original-63", "original-64", "original-50", "original-38", "original-39", "original-51", "original-65", "original-40", "original-52", "original-66", "original-53", "original-58", "original-45", "original-33", "original-31", "original-32", "original-44", "original-57", "original-56", "original-43", "original-3", "original-4", "original-55", "original-70", "original-71", "original-72", "original-73", "original-74", "original-76", "original-75", "original-77", "original-78", "original-79", "original-80", "original-81", "original-82", "original-12", "original-11", "original-10", "original-1", "original-7", "original-6", "original-8", "original-9", "original-13", "original-14", "original-15", "original-16", "original-17", "original-18", "original-19", "original-20", "original-67", "original-54", "original-41", "original-42", "original-68", "original-69", "original-84", "original-83", "original-85", "original-108", "original-109", "original-110", "original-111", "original-112", "original-5", "original-113", "original-114", "original-115", "original-104", "original-105", "original-95", "original-97", "original-96", "original-92", "original-94", "original-90", "original-89", "original-86", "original-30", "original-29", "original-21", "original-25", "original-87", "original-103", "original-88", "original-91", "original-93", "original-106", "original-107", "original-98", "original-99", "original-100", "original-101", "original-102", "original-28", "original-27", "original-26", "original-24", "original-23", "original-22", "original-2", "original-34", "original-35", "original-36", "original-37", "original-48", "original-47", "original-46", "original-59", "original-60", "original-61", "original-62"]}]